LICENSE
MANIFEST.in
README.rst
runtests.sh
setup.py
examples/__init__.py
examples/basic.py
examples/web.py
helo/__init__.py
helo/_builder.py
helo/_const.py
helo/_helper.py
helo/_logging.py
helo/db.py
helo/err.py
helo/g.py
helo/model.py
helo/types.py
helo/util.py
helo.egg-info/PKG-INFO
helo.egg-info/SOURCES.txt
helo.egg-info/dependency_links.txt
helo.egg-info/not-zip-safe
helo.egg-info/requires.txt
helo.egg-info/top_level.txt
tests/__init__.py
tests/case.py
tests/test_db.py
tests/test_g.py
tests/test_model.py
tests/test_query.py
tests/test_types.py