Metadata-Version: 1.2
Name: helo
Version: 0.0.6
Summary: Helo is a simple and small low-level asynchronous ORM using Python asyncio.
Home-page: https://github.com/at7h/helo
Author: at7h
Author-email: g@at7h.com
License: MIT
Keywords: orm asyncio mysql aiomysql pymysql python python3 async/await web
Platform: any
Classifier: Programming Language :: Python :: 3
Classifier: Programming Language :: Python :: 3.7
Classifier: Programming Language :: Python :: 3.8
Classifier: Intended Audience :: Developers
Requires-Python: >=3.7
